fileplayer/__init__.py
fileplayer/config.py
fileplayer/globa.py
fileplayer/main.py
fileplayer/main_window.py
fileplayer/timer.py
fileplayer/widgets.py
file_player-1.0.0a27.dist-info/LICENSE
file_player-1.0.0a27.dist-info/METADATA
file_player-1.0.0a27.dist-info/WHEEL
file_player-1.0.0a27.dist-info/entry_points.txt
file_player-1.0.0a27.dist-info/top_level.txt
file_player-1.0.0a27.dist-info/RECORD
