Metadata-Version: 2.1
Name: file-player
Version: 1.0.0a27
Summary: A music player using the file system to order/structure files (rather than audio tags)
Home-page: https://gitlab.com/SunyataZero/file-player
Author: Tord Dellsén
Author-email: tord.dellsen@gmail.com
License: GPLv3
Platform: UNKNOWN
Classifier: License :: OSI Approved :: GNU General Public License v3 (GPLv3)
Classifier: Programming Language :: Python
Classifier: Programming Language :: Python :: 3
Classifier: Development Status :: 2 - Pre-Alpha
Classifier: Intended Audience :: End Users/Desktop
Requires-Python: >=3.8.0
Requires-Dist: PyQt5 (>=5.15.2)
